iterchunk/__init__.py
iterchunk/chunking.py
iterchunk/tests/chuncking_test.py
iterchunk-0.0.2.dev0.dist-info/LICENSE
iterchunk-0.0.2.dev0.dist-info/WHEEL
iterchunk-0.0.2.dev0.dist-info/METADATA
iterchunk-0.0.2.dev0.dist-info/RECORD
