Metadata-Version: 2.1
Name: iterchunk
Version: 0.0.2.dev0
Summary: Split an iterable into chunks in Python.
Home-page: https://github.com/ianlini/iterchunk
License: MIT
Author: Ian Lin
Author-email: you@example.com
Requires-Python: >=2.7, !=3.0.*, !=3.1.*, !=3.2.*, !=3.3.*, !=3.4.*
Classifier: License :: OSI Approved :: MIT License
Classifier: Programming Language :: Python :: 2
Classifier: Programming Language :: Python :: 2.7
Classifier: Programming Language :: Python :: 3
Classifier: Programming Language :: Python :: 3.5
Classifier: Programming Language :: Python :: 3.6
Classifier: Programming Language :: Python :: 3.7
Classifier: Topic :: Utilities
Project-URL: Repository, https://github.com/ianlini/iterchunk
